mavisim/__init__.py
mavisim/astromsim.py
mavisim/generate_image.py
mavisim/source.py
mavisim/util.py
mavisim_gpu-1.1.10.dist-info/LICENSE
mavisim_gpu-1.1.10.dist-info/METADATA
mavisim_gpu-1.1.10.dist-info/WHEEL
mavisim_gpu-1.1.10.dist-info/top_level.txt
mavisim_gpu-1.1.10.dist-info/RECORD
