Metadata-Version: 2.1
Name: mavisim-gpu
Version: 1.1.10
Summary: Tool for simulating MAVIS images
Home-page: https://github.com/smonty93/mavisim
Author: Stephanie Monty
Author-email: stephanie.monty@anu.edu.au
Classifier: Programming Language :: Python :: 3
Classifier: License :: OSI Approved :: GNU General Public License (GPL)
Classifier: Operating System :: OS Independent
Requires-Python: >=3.7
License-File: LICENSE
Requires-Dist: astropy
Requires-Dist: scipy
Requires-Dist: torch
Requires-Dist: opt-einsum
Requires-Dist: numpy
Requires-Dist: tqdm
